nautilus/__init__.py
nautilus/database.py
nautilus/api/__init__.py
nautilus/api/filter.py
nautilus/api/schema.py
nautilus/api/endpoints/__init__.py
nautilus/api/endpoints/requestHandlers/__init__.py
nautilus/api/endpoints/requestHandlers/apiQuery.py
nautilus/api/endpoints/requestHandlers/graphiql.py
nautilus/api/endpoints/requestHandlers/graphql.py
nautilus/api/endpoints/static/build/scripts/graphiql.js
nautilus/api/endpoints/static/build/styles/graphiql.css
nautilus/api/endpoints/static/src/scripts/graphiql.js
nautilus/api/endpoints/static/src/styles/graphiql.css
nautilus/api/endpoints/templates/graphiql.html
nautilus/api/util/__init__.py
nautilus/api/util/arg_string_from_dict.py
nautilus/api/util/build_native_type_dictionary.py
nautilus/api/util/convert_typestring_to_api_native.py
nautilus/api/util/create_model_schema.py
nautilus/api/util/fields_for_model.py
nautilus/api/util/generate_api_schema.py
nautilus/api/util/graph_entity.py
nautilus/api/util/graphql_mutation_from_summary.py
nautilus/api/util/graphql_type_from_summary.py
nautilus/api/util/parse_string.py
nautilus/api/util/query_for_model.py
nautilus/api/util/serialize_native_type.py
nautilus/api/util/summarize_crud_mutation.py
nautilus/api/util/summarize_mutation.py
nautilus/api/util/summarize_mutation_io.py
nautilus/api/util/walk_query.py
nautilus/auth/__init__.py
nautilus/auth/decorators.py
nautilus/auth/models/__init__.py
nautilus/auth/models/userPassword.py
nautilus/auth/models/fields/__init__.py
nautilus/auth/models/fields/password.py
nautilus/auth/models/mixins/__init__.py
nautilus/auth/models/mixins/hasPassword.py
nautilus/auth/models/mixins/user.py
nautilus/auth/primitives/__init__.py
nautilus/auth/primitives/passwordHash.py
nautilus/auth/util/__init__.py
nautilus/auth/util/generate_session_token.py
nautilus/auth/util/random_string.py
nautilus/auth/util/read_session_token.py
nautilus/auth/util/token_encryption_algorithm.py
nautilus/config/__init__.py
nautilus-0.5.2.dist-info/DESCRIPTION.rst
nautilus-0.5.2.dist-info/METADATA
nautilus-0.5.2.dist-info/RECORD
nautilus-0.5.2.dist-info/WHEEL
nautilus-0.5.2.dist-info/entry_points.txt
nautilus-0.5.2.dist-info/metadata.json
nautilus-0.5.2.dist-info/top_level.txt
