Metadata-Version: 2.0
Name: nautilus
Version: 0.5.2
Summary: A library for creating event-driven microservice applications
Home-page: https://github.com/AlecAivazis/nautilus
Author: Alec Aivazis
Author-email: alec@aivazis.com
License: UNKNOWN
Download-URL: https://github.com/aaivazis/nautilus/tarball/0.5.0
Keywords: microservice,asyncio,graphql
Platform: UNKNOWN
Requires-Dist: PyJWT
Requires-Dist: aiohttp
Requires-Dist: aiohttp-cors
Requires-Dist: aiohttp-jinja2
Requires-Dist: aiohttp-session
Requires-Dist: aiokafka
Requires-Dist: bcrypt
Requires-Dist: click
Requires-Dist: cryptography
Requires-Dist: graphene
Requires-Dist: jinja2
Requires-Dist: nose2
Requires-Dist: peewee
Requires-Dist: pytest
Requires-Dist: python-consul
Requires-Dist: uvloop
